_kSpider_internal.cpython-38-x86_64-linux-gnu.so
kSpider.libs/libbz2-a273e504.so.1.0.6
kSpider.libs/libgomp-a34b3233.so.1.0.0
internal/kSpider_internal.py
internal/__init__.py
kSpider-2.3.2.dist-info/WHEEL
kSpider-2.3.2.dist-info/LICENSE
kSpider-2.3.2.dist-info/RECORD
kSpider-2.3.2.dist-info/top_level.txt
kSpider-2.3.2.dist-info/METADATA
kSpider-2.3.2.dist-info/entry_points.txt
kSpider2/ks_clustering.py
kSpider2/kSpider_version.py
kSpider2/ks_pairwise.py
kSpider2/ks_export.py
kSpider2/customLogger.py
kSpider2/click_context.py
kSpider2/ks_dataset_indexing.py
kSpider2/ks_fastx_to_kfs.py
kSpider2/kSpider_main.py
kSpider2/ks_index.py
kSpider2/__init__.py
