Metadata-Version: 2.1
Name: kSpider
Version: 2.3.2
Summary: A simple yet powerful sequence clustering tool
License: BSD 3-Clause
Project-URL: Bug Reports, https://github.com/dib-lab/kSpider/issues
Project-URL: Source, https://github.com/dib-lab/kSpider/issues
Classifier: License :: OSI Approved :: Apache Software License
Classifier: Development Status :: 3 - Alpha
Classifier: Operating System :: POSIX :: Linux
Classifier: Programming Language :: Python
Classifier: Programming Language :: Python :: 3
Classifier: Programming Language :: Python :: 3.6
Classifier: Programming Language :: Python :: 3.7
Classifier: Programming Language :: Python :: 3.8
Classifier: Programming Language :: Python :: 3.9
Classifier: Programming Language :: Python :: 3.10
Classifier: Programming Language :: Python :: 3.11
Requires-Python: >=3.6
License-File: LICENSE
Requires-Dist: Click
Requires-Dist: pandas
Requires-Dist: scipy
Requires-Dist: numpy
Requires-Dist: rustworkx
Requires-Dist: tqdm
